Workbook
Name Digestibilidad: #REF!
Name Digestibilidad: #REF!

Sheet Cotizador
A1: Cotizador | I1: ACTUALIZADOS ✅
A2: Prestaciones sin valor COBICO, o cuyo valor COBICO es inferior al costo de derivación total | H2: 0.35
A4: =Delgado!A3 -> Valores actualizados al mes de ABRIL2026 | F4: 0.05
A5: Prestaciones | B5: Derivación | C5: Derivante | D5: Envío | E5: Viaticos | F5: Costo Interno | G5: COBICO | H5: Importe
A6: ALEX 2 | B6: 607684 | C6: CIBIC | D6: 20000 | F6: =B6*($F$4) -> 30384.2 | H6: =+SUM(B6:F6)*(1+$H$2) -> 888392.07
A7: TPMT TIOPURINA METILTRANSFERASA | B7: 193701.96 | C7: MANLAB | D7: 20000 | E7: 0 | F7: =B7*($F$4) -> 9685.098 | H7: =+SUM(B7:F7)*(1+$H$2) -> 301572.53
A8: DAO | B8: 204016 | C8: MANLAB | D8: 20000 | E8: 0 | F8: =B8*($F$4) -> 10200.8 | H8: =+SUM(B8:F8)*(1+$H$2) -> 316192.68
A9: POLIMORFIMOS DE DAO | B9: 299909 | C9: CIBIC | D9: 20000 | E9: 0 | F9: =B9*($F$4) -> 14995.45 | H9: =+SUM(B9:F9)*(1+$H$2) -> 452121.01
A10: TRIPTASA | B10: 159424.52 | C10: MANLAB | D10: 20000 | E10: 0 | F10: =B10*($F$4) -> 7971.226 | H10: =+SUM(B10:F10)*(1+$H$2) -> 252984.26
A11: TRIPTASA MAR DEL PLATA | B11: =52311*1.1 -> 57542.1 | C11: LITWIN | D11: 20000 | E11: 0 | F11: =B11*($F$4) -> 2877.105 | H11: =+SUM(B11:F11)*(1+$H$2) -> 108565.93
A12: PLGF | B12: 55980.31 | C12: GORNITZ | D12: 20000 | E12: 0 | F12: =B12*($F$4) -> 2799.0155 | H12: =+SUM(B12:F12)*(1+$H$2) -> 106352.09
A13: Panel inmunologico miositis | B13: 163503 | C13: CIBIC | D13: 20000 | E13: 0 | F13: =B13*($F$4) -> 8175.15 | H13: =+SUM(B13:F13)*(1+$H$2) -> 258765.5
A14: Levetirazetam | B14: 5290 | C14: LERDA | D14: 5000 | E14: 0 | F14: =B14*($F$4) -> 264.5 | H14: =+SUM(B14:F14)*(1+$H$2) -> 14248.575
A15: PARVOVIRUS B19 (PCR) | B15: 67986 | C15: CIBIC | D15: 20000 | E15: 0 | F15: =B15*($F$4) -> 3399.3 | H15: =+SUM(B15:F15)*(1+$H$2) -> 123370.15
A16: PEPTIDO INTESTINAL VASOACTIVO (VIP) | B16: 780938.78 | C16: GORNITZ | D16: 20000 | E16: 0 | F16: =B16*($F$4) -> 39046.939 | H16: =+SUM(B16:F16)*(1+$H$2) -> 1133980.7
A17: MICROBIOMA INTESTINAL | B17: 297460 | C17: CIBIC | D17: 20000 | E17: 0 | F17: =B17*($F$4) -> 14873 | H17: =+SUM(B17:F17)*(1+$H$2) -> 448649.55
A18: VEGF | B18: 394294.45 | C18: MANLAB | D18: 20000 | E18: 0 | F18: =B18*($F$4) -> 19714.722 | H18: =+SUM(B18:F18)*(1+$H$2) -> 585912.38 | I18: REYNA | J18: FPM | K18: CIBIC | L18: DER FPM | N18: COPAGO APROSS
A19: FENOTIPO | B19: 250566 | C19: CIBIC | D19: 20000 | E19: 0 | F19: =B19*($F$4) -> 12528.3 | G19: 421500 | H19: =+SUM(B19:F19)*(1+$H$2) -> 382177.3 | I19: =H19*0.98 -> 374533.76 | J19: =I19-L19 -> 44810.009 | K19: =I19-B19 -> 123967.76 | L19: =329723.75 -> 329723.75 | M19: =I19/B19-1 -> 0.49475092
A20: CARIOTIPO M. OSEA | B20: 90683.77 | C20: FPM | D20: 5000 | E20: 0 | F20: =B20*($F$4) -> 4534.1885 | H20: =+SUM(B20:F20)*(1+$H$2) -> 135294.24 | I20: =H20*0.98 -> 132588.36 | J20: =I20-L20 -> 41904.589 | K20: =I20-B20 -> 41904.589 | L20: 90683.77 | M20: =I20/B20-1 -> 0.4620958 | N20: 77000
A21: CARIOTIPO SANGRE | B21: 90683.77 | C21: FPM | D21: 5000 | E21: 0 | F21: =B21*($F$4) -> 4534.1885 | H21: =+SUM(B21:F21)*(1+$H$2) -> 135294.24 | I21: =H21*0.98 -> 132588.36 | J21: =I21-L21 -> 41904.589 | K21: =I21-B21 -> 41904.589 | L21: 90683.77 | M21: =I21/B21-1 -> 0.4620958 | N21: 87450
A22: FISH | B22: 414960 | C22: FUNDACION | D22: 5000 | E22: 0 | F22: =B22*($F$4) -> 20748 | H22: =+SUM(B22:F22)*(1+$H$2) -> 594955.8
A23: GASES EN SANGRE | B23: 4071.58 | C23: ALLENDE | D23: 5000 | E23: 0 | F23: =B23*($F$4) -> 203.579 | H23: =+SUM(B23:F23)*(1+$H$2) -> 12521.465
A24: NEFA | B24: 5425.11 | C24: GORNITZ | D24: 20000 | E24: 0 | F24: =B24*($F$4) -> 271.2555 | H24: =+SUM(B24:F24)*(1+$H$2) -> 34690.093
A25: inhibina b | B25: 80298.52 | C25: GORNITZ | D25: 20000 | E25: 0 | F25: =B25*($F$4) -> 4014.926 | H25: =+SUM(B25:F25)*(1+$H$2) -> 140823.15
A26: BCRA 29018 | B26: 145308 | C26: CIBIC | D26: 20000 | E26: 0 | F26: =B26*($F$4) -> 7265.4 | H26: =+SUM(B26:F26)*(1+$H$2) -> 232974.09
A27: CANDIDAS IGM | B27: 45226.19 | C27: GORNITZ | D27: 20000 | E27: 0 | F27: =B27*($F$4) -> 2261.3095 | H27: =+SUM(B27:F27)*(1+$H$2) -> 91108.124
A28: CALPROTECTINA | B28: 30542.33 | C28: MANLAB | D28: 20000 | E28: 0 | F28: =B28*($F$4) -> 1527.1165 | H28: =+SUM(B28:F28)*(1+$H$2) -> 70293.753
A29: ACIDOS | B29: 89361.83 | C29: MANLAB | D29: 20000 | E29: 0 | F29: =B29*($F$4) -> 4468.0915 | H29: =+SUM(B29:F29)*(1+$H$2) -> 153670.39
A30: ANTIFUNGICO | B30: 10201.14 | C30: GORNITZ | D30: 20000 | E30: 0 | F30: =B30*($F$4) -> 510.057 | H30: =+SUM(B30:F30)*(1+$H$2) -> 41460.116
A31: penfigoides | B31: 15392 | C31: CIBIC | D31: 20000 | E31: 0 | F31: =B31*($F$4) -> 769.6 | H31: =+SUM(B31:F31)*(1+$H$2) -> 48818.16
A32: IGLON 5 | B32: 337405 | C32: CIBIC | D32: 20000 | E32: 0 | F32: =B32*($F$4) -> 16870.25 | H32: =+SUM(B32:F32)*(1+$H$2) -> 505271.59
A33: PANEL MIELOIDE | B33: 1259832 | C33: CIBIC | D33: 20000 | E33: 0 | F33: =B33*($F$4) -> 62991.6 | H33: =+SUM(B33:F33)*(1+$H$2) -> 1812811.9
... A37: anticuerpo encefalitis panel | B37: 259935.03 | C37: gornitz | D37: 20000 | E37: 0 | F37: =B37*($F$4) -> 12996.752 | H37: =+SUM(B37:F37)*(1+$H$2) -> 395457.91
A38: anticuerpo encefalitis panel | B38: =B37*1.02 -> 265133.73 | C38: gornitz | D38: 20000 | E38: 0 | F38: =B38*($F$4) -> 13256.687 | H38: =+SUM(B38:F38)*(1+$H$2) -> 402827.06
A39: MICROBIOTA | B39: 272418 | C39: CIBIC | D39: 20000 | E39: 0 | F39: =B39*($F$4) -> 13620.9 | H39: =+SUM(B39:F39)*(1+$H$2) -> 413152.52
A40: GAD | B40: 19466 | C40: CIBIC | D40: 20000 | E40: 0 | F40: =B40*($F$4) -> 973.3 | H40: =+SUM(B40:F40)*(1+$H$2) -> 54593.055
A41: IA 2A | B41: 40486 | C41: CIBIC | D41: 20000 | E41: 0 | F41: =B41*($F$4) -> 2024.3 | H41: =+SUM(B41:F41)*(1+$H$2) -> 84388.905
A42: ZN T8A | B42: 84266.69 | C42: MANLAB | D42: 20000 | E42: 0 | F42: =B42*($F$4) -> 4213.3345 | H42: =+SUM(B42:F42)*(1+$H$2) -> 146448.03
A43: IAA | B43: 10743 | C43: CIBIC | D43: 20000 | E43: 0 | F43: =B43*($F$4) -> 537.15 | H43: =+SUM(B43:F43)*(1+$H$2) -> 42228.202
A44: PANLE HEPATICO | B44: 179871 | C44: gornitz | D44: 20000 | E44: 0 | F44: =B44*($F$4) -> 8993.55 | H44: =+SUM(B44:F44)*(1+$H$2) -> 281967.14
A45: MTHFR | B45: 26989.03 | C45: manLAB | D45: 20000 | E45: 0 | F45: =B45*($F$4) -> 1349.4515 | H45: =+SUM(B45:F45)*(1+$H$2) -> 65256.95
A46: JAK | B46: 62727 | C46: FUNDACION | D46: 5000 | E46: 0 | F46: =B46*($F$4) -> 3136.35 | H46: =+SUM(B46:F46)*(1+$H$2) -> 95665.523
A47: EXOMA COMPLETO | B47: 570000 | C47: CIBIC | D47: 5000 | F47: =+B47*0.05 -> 28500 | H47: =+SUM(B47:F47)*(1+$H$2) -> 814725
A48: FACTOR PLACENTARIO | B48: 35399 | C48: CIBIC | D48: 5000 | F48: =+B48*0.1 -> 3539.9 | H48: =+SUM(B48:F48)*(1+$H$2) -> 59317.515
A49: ACIDO METALOMINICO | B49: 102652.9 | C49: MANLAB | D49: 20000 | E49: 0 | F49: =B49*($F$4) -> 5132.645 | H49: =+SUM(B49:F49)*(1+$H$2) -> 172510.49
A50: MUTACION GEN GILBERT | B50: 86684 | C50: CIBIC | D50: 20000 | E50: 0 | F50: =B50*($F$4) -> 4334.2 | H50: =+SUM(B50:F50)*(1+$H$2) -> 149874.57
A51: FIS 9.22 | B51: 257898 | C51: CIBIC | D51: 20000 | E51: 0 | F51: =B51*($F$4) -> 12894.9 | H51: =+SUM(B51:F51)*(1+$H$2) -> 392570.41
A52: cuali | B52: 146218.8 | C52: FUNDACION | D52: 5000 | E52: 0 | F52: =B52*($F$4) -> 7310.94 | H52: =+SUM(B52:F52)*(1+$H$2) -> 214015.15
A53: ACIDOS GRASOS | B53: 103486.14 | C53: MANLAB | D53: 20000 | E53: 0 | F53: =B53*($F$4) -> 5174.307 | H53: =+SUM(B53:F53)*(1+$H$2) -> 173691.6
A54: JAK V617F | B54: 57990.84 | C54: MANLAB | D54: 20000 | E54: 0 | F54: =B54*($F$4) -> 2899.542 | H54: =+SUM(B54:F54)*(1+$H$2) -> 109202.02
A55: PANEL CANCER HEREDITARIO MAMA - OVARIO - basico | B55: 408803 | C55: CIBIC | D55: 20000 | E55: 0 | F55: =B55*($F$4) -> 20440.15 | H55: =+SUM(B55:F55)*(1+$H$2) -> 606478.25
A56: PANEL CANCER HEREDITARIO MAMA - OVARIO - ampliado | B56: 458355 | C56: CIBIC | D56: 20000 | E56: 0 | F56: =B56*($F$4) -> 22917.75 | H56: =+SUM(B56:F56)*(1+$H$2) -> 676718.21
A57: HLA CLASE I LOCUS A | B57: 110849 | C57: CIBIC | D57: 20000 | E57: 0 | F57: =B57*($F$4) -> 5542.45 | H57: =+SUM(B57:F57)*(1+$H$2) -> 184128.46
A58: HLA CLASE I LOCUS B | B58: 110849 | C58: CIBIC | D58: 20000 | E58: 0 | F58: =B58*($F$4) -> 5542.45 | H58: =+SUM(B58:F58)*(1+$H$2) -> 184128.46
A59: HLA CLASE II LOCUS DR | B59: 110849 | C59: CIBIC | D59: 20000 | E59: 0 | F59: =B59*($F$4) -> 5542.45 | H59: =+SUM(B59:F59)*(1+$H$2) -> 184128.46
A60: CROSS MATCH - PANEL FASE SOLIDA | B60: 180550 | C60: FUNDACION | D60: 5000 | E60: 0 | F60: =B60*($F$4) -> 9027.5 | H60: =+SUM(B60:F60)*(1+$H$2) -> 262679.62
... A62: ISOELECTROFUCUS DE TRANSFERRINA | B62: 199692 | C62: CIBIC | D62: 20000 | E62: 0 | F62: =B62*($F$4) -> 9984.6 | H62: =+SUM(B62:F62)*(1+$H$2) -> 310063.41
A63: DOSAJE DE LEVETIRACETAM | B63: 9800 | C63: LERDA | D63: 5000 | F63: =B63*($F$4) -> 490 | H63: =+SUM(B63:F63)*(1+$H$2) -> 20641.5
A64: Inmunoglobulina E | B64: 1559.7 | C64: MANLAB | D64: 5000 | F64: =B64*($F$4) -> 77.985 | G64: 14050 | H64: =G64*0.9 -> 12645
A65: Igg coronavirus | B65: 24541.06 | C65: MANLAB | D65: 5000 | F65: =B65*($F$4) -> 1227.053 | H65: =+SUM(B65:F65)*(1+$H$2) -> 41536.953
A66: Sustancia Amieloide | B66: 219644.09 | C66: MANLAB | D66: 5000 | F66: =B66*($F$4) -> 10982.204 | H66: =+SUM(B66:F66)*(1+$H$2) -> 318095.5
A67: AMINOACIDOS CUANTITATIVOS | B67: 94877.56 | C67: MANLAB | D67: 5000 | F67: =B67*($F$4) -> 4743.878 | H67: =+SUM(B67:F67)*(1+$H$2) -> 141238.94
A68: COLAGENOS | B68: 224135.5 | C68: MANLAB | D68: 5000 | F68: =B68*($F$4) -> 11206.775 | H68: =+SUM(B68:F68)*(1+$H$2) -> 324462.07
A69: PCR PARA NEISSERIA GONORRHOEAE | B69: 37980.82 | C69: FUNDACION | D69: 5000 | F69: =B69*($F$4) -> 1899.041 | H69: =+SUM(B69:F69)*(1+$H$2) -> 60587.812
A70: PCR PARA MYCOPLASMA GENITALIUM | B70: 45100.07 | C70: FUNDACION | D70: 5000 | F70: =B70*($F$4) -> 2255.0035 | H70: =+SUM(B70:F70)*(1+$H$2) -> 70679.349
A71: TB-IGRA (Ensayo de Liberación de Interferón Gamma) | B71: 136550.13 | C71: GORNITZ | D71: 5000 | F71: =B71*($F$4) -> 6827.5065 | H71: =+SUM(B71:F71)*(1+$H$2) -> 200309.81
A72: ACIDO METILMALONICO | B72: 109897.9 | C72: manlab | D72: 5000 | F72: =B72*($F$4) -> 5494.895 | H72: =+SUM(B72:F72)*(1+$H$2) -> 162530.27
A73: MICROARRAY 750K | B73: 487632 | C73: fundacion | D73: 5000 | F73: =B73*($F$4) -> 24381.6 | H73: =+SUM(B73:F73)*(1+$H$2) -> 697968.36
A74: CALRETICULINA | B74: 84000.39 | C74: manlab | D74: 5000 | F74: =B74*($F$4) -> 4200.0195 | H74: =+SUM(B74:F74)*(1+$H$2) -> 125820.55

Sheet Federacion-PAMI
H1: PRESUPUESTO | I1: FACTURA A
B2: COBRADO | H2: A ENVIAR | I2: FEDERACION
A3: VILLAGRA BEATRIZ | B3: Costo | D3: UB | E3: Pami | F3: COBICO | H3: Importe | I3: Facturado | L3: NBU | M3: 450
A4: Inmunofijación Sérica | B4: =31384.55+6000 -> 37384.55 | D4: 50 | E4: =+D4*$M$3 -> 22500 | F4: 42500 | H4: =+F4*0.97 -> 41225 | I4: =+(F4-E4)*$M$5 -> 18800 | L4: Descuento | M4: 0.9
A5: Inmunofijación Urinaria | B5: =39226.54+6000 -> 45226.54 | D5: 50 | E5: =+D5*$M$3 -> 22500 | F5: 42500 | H5: =+F5*0.97 -> 41225 | I5: =+(F5-E5)*$M$5 -> 18800 | L5: Descuento | M5: 0.94
H6: =SUM(H4:H5) -> 82450 | I6: =SUM(I4:I5) -> 37600
A8: CARBONE PICARDO JULIO | B8: COBRADO | H8: Importe
A9: Inmunofijación Sérica | B9: =31384.55+6000 -> 37384.55 | D9: 50 | E9: =+D9*$M$3 -> 22500 | F9: 42500 | H9: =+F9*0.97 -> 41225 | I9: =+(F9-E9)*$M$5 -> 18800
A10: Inmunofijación Urinaria | B10: =39226.54+6000 -> 45226.54 | D10: 50 | E10: =+D10*$M$3 -> 22500 | F10: 42500 | H10: =+F10*0.97 -> 41225 | I10: =+(F10-E10)*$M$5 -> 18800
A11: Cadena liviana libre | B11: =6000+65715.56 -> 71715.56 | D11: 100 | E11: =+D11*$M$3 -> 45000 | F11: 110500 | H11: =+F11*0.9 -> 99450 | I11: =+(F11-E11)*$M$4 -> 58950
A12: Cadena liviana libre | B12: =6000+62243.75 -> 68243.75 | D12: 100 | E12: =+D12*$M$3 -> 45000 | F12: 110500 | H12: =+F12*0.9 -> 99450 | I12: =+(F12-E12)*$M$4 -> 58950
H13: =SUM(H9:H12) -> 281350 | I13: =SUM(I9:I12) -> 155500
A15: MALDONADO ALEJANDRO CESAR | B15: COBRADO | H15: Importe
A16: TCR | B16: 241818 | D16: 300 | E16: =+D16*$M$16 -> 159150 | F16: 300000 | H16: =F16*M17 -> 282000 | I16: =H16-E16 -> 122850 | L16: NBU | M16: =(671+390)/2 -> 530.5
L17: Descuento | M17: 0.94
A18: GERMANETTO NOEMI CATALINA | B18: PENDIENTE DE COBRO
A19: Cadena liviana Kappa y Lambda sérico | B19: 7605.21 | D19: 40 | E19: =D19*$M$19 -> 14800 | F19: 40000 | H19: =F19*$M$20 -> 32000 | I19: =H19-E19 -> 17200 | J19: =H19/B19-1 -> 3.2076419 | L19: NBU | M19: 370
A20: Inmunofijación sérica | B20: 33619.13 | D20: 50 | E20: =D20*$M$19 -> 18500 | F20: 50000 | H20: =F20*$M$21 -> 45000 | I20: =H20-E20 -> 26500 | J20: =H20/B20-1 -> 0.33852363 | L20: Descuento | M20: 0.8
A21: Inmunofijación urinaria | B21: 42019.46 | D21: 50 | E21: =D21*$M$19 -> 18500 | F21: 50000 | H21: =F21*$M$21 -> 45000 | I21: =H21-E21 -> 26500 | J21: =H21/B21-1 -> 0.070932373 | L21: Descuento | M21: 0.9
A22: Microglobulina Beta2 | B22: 1864.12 | D22: 18 | E22: =D22*$M$19 -> 6660 | F22: 18000 | H22: =F22*$M$20 -> 14400 | I22: =H22-E22 -> 7740 | J22: =H22/B22-1 -> 6.7248246
A23: Creatinina | B23: 1000 | D23: 3 | E23: =D23*$M$19 -> 1110 | F23: 3000 | H23: =F23*$M$20 -> 2400 | I23: =H23-E23 -> 1290 | J23: =H23/B23-1 -> 1.4
A24: Eritrocedimentación | B24: 1000 | D24: 2 | E24: =D24*$M$19 -> 740 | F24: 2000 | H24: =F24*$M$20 -> 1600 | I24: =H24-E24 -> 860 | J24: =H24/B24-1 -> 0.6
A25: Hemograma | B25: 1000 | D25: 5 | E25: =D25*$M$19 -> 1850 | F25: 5000 | H25: =F25*$M$20 -> 4000 | I25: =H25-E25 -> 2150 | J25: =H25/B25-1 -> 3
A26: Inmunoglobulina A | B26: 616.85 | D26: 5 | E26: =D26*$M$19 -> 1850 | F26: 5000 | H26: =F26*$M$20 -> 4000 | I26: =H26-E26 -> 2150 | J26: =H26/B26-1 -> 5.4845586
A27: Inmunoglobulina E | B27: 1095.09 | D27: 10 | E27: =D27*$M$19 -> 3700 | F27: 10000 | H27: =F27*$M$20 -> 8000 | I27: =H27-E27 -> 4300 | J27: =H27/B27-1 -> 6.3053356
A28: Inmunoglobulina G | B28: 493.48 | D28: 5 | E28: =D28*$M$19 -> 1850 | F28: 5000 | H28: =F28*$M$20 -> 4000 | I28: =H28-E28 -> 2150 | J28: =H28/B28-1 -> 7.1056983
A29: Inmunoglobulina M | B29: 493.48 | D29: 5 | E29: =D29*$M$19 -> 1850 | F29: 5000 | H29: =F29*$M$20 -> 4000 | I29: =H29-E29 -> 2150 | J29: =H29/B29-1 -> 7.1056983
A30: Recuento de plaquetas | B30: 1000 | D30: 2 | E30: =D30*$M$19 -> 740 | F30: 2000 | H30: =F30*$M$20 -> 1600 | I30: =H30-E30 -> 860 | J30: =H30/B30-1 -> 0.6
A31: Proteinograma | B31: 2906.33 | D31: 12 | E31: =D31*$M$19 -> 4440 | F31: 12000 | H31: =F31*$M$20 -> 9600 | I31: =H31-E31 -> 5160 | J31: =H31/B31-1 -> 2.3031349
A32: Uremia | B32: 1000 | D32: 1.5 | E32: =D32*$M$19 -> 555 | F32: 1500 | H32: =F32*$M$20 -> 1200 | I32: =H32-E32 -> 645 | J32: =H32/B32-1 -> 0.2
A33: Glucemia | B33: 1000 | D33: 1.5 | E33: =D33*$M$19 -> 555 | F33: 1500 | H33: =F33*$M$20 -> 1200 | I33: =H33-E33 -> 645 | J33: =H33/B33-1 -> 0.2
... A39: TSH | B39: 428.93 | D39: 9 | E39: =D39*$M$19 -> 3330 | F39: 9000 | H39: =F39*$M$20 -> 7200 | I39: =H39-E39 -> 3870 | J39: =H39/B39-1 -> 15.785956
H40: =SUM(H19:H39) -> 193200 | I40: =SUM(I19:I22) -> 77940
A42: ORTIZ EDITH NORMA | B42: Costo | C42: Envio | D42: UB | E42: Pami | F42: COBICO
A43: Hemograma | B43: 1000 | D43: 5 | E43: =D43*$M$43 -> 2530 | F43: 5000 | H43: =F43*$M$44 -> 4000 | I43: =H43-E43 -> 1470 | J43: =H43/B43-1 -> 3 | K43: =E43/B43-1 -> 1.53 | L43: NBU | M43: 506
A44: Cobre serico | B44: 12475.5 | C44: =(D44/$C$64)*$B$64 -> 1677.0186 | D44: 20 | E44: =D44*$M$43 -> 10120 | F44: 20000 | H44: =F44*$M$44 -> 16000 | I44: =H44-E44+C44 -> 7557.0186 | J44: =H44/B44-1 -> 0.28251373 | K44: =E44/B44-1 -> -0.18881007 | L44: Descuento | M44: 0.8
A45: Colesterol total | B45: 1000 | D45: 1.5 | E45: =D45*$M$43 -> 759 | F45: 1500 | H45: =F45*$M$44 -> 1200 | I45: =H45-E45 -> 441 | J45: =H45/B45-1 -> 0.2 | K45: =E45/B45-1 -> -0.241 | L45: Descuento | M45: 0.9
A46: Creatinina | B46: 1000 | D46: 3 | E46: =D46*$M$43 -> 1518 | F46: 3000 | H46: =F46*$M$44 -> 2400 | I46: =H46-E46 -> 882 | J46: =H46/B46-1 -> 1.4 | K46: =E46/B46-1 -> 0.518
A47: Eritrosedimentación | B47: 1000 | D47: 2 | E47: =D47*$M$43 -> 1012 | F47: 2000 | H47: =F47*$M$44 -> 1600 | I47: =H47-E47 -> 588 | J47: =H47/B47-1 -> 0.6 | K47: =E47/B47-1 -> 0.012
A48: Glucemia | B48: 1000 | D48: 1.5 | E48: =D48*$M$43 -> 759 | F48: 1500 | H48: =F48*$M$44 -> 1200 | I48: =H48-E48 -> 441 | J48: =H48/B48-1 -> 0.2 | K48: =E48/B48-1 -> -0.241
A49: GOT | B49: 1000 | D49: 1.5 | E49: =D49*$M$43 -> 759 | F49: 1500 | H49: =F49*$M$44 -> 1200 | I49: =H49-E49 -> 441 | J49: =H49/B49-1 -> 0.2 | K49: =E49/B49-1 -> -0.241
A50: GPT | B50: 1000 | D50: 1.5 | E50: =D50*$M$43 -> 759 | F50: 1500 | H50: =F50*$M$44 -> 1200 | I50: =H50-E50 -> 441 | J50: =H50/B50-1 -> 0.2 | K50: =E50/B50-1 -> -0.241
A51: FAL | B51: 1000 | D51: 1.5 | E51: =D51*$M$43 -> 759 | F51: 1500 | H51: =F51*$M$44 -> 1200 | I51: =H51-E51 -> 441 | J51: =H51/B51-1 -> 0.2 | K51: =E51/B51-1 -> -0.241
A52: BILI | B52: 1000 | D52: 2 | E52: =D52*$M$43 -> 1012 | F52: 2000 | H52: =F52*$M$44 -> 1600 | I52: =H52-E52 -> 588 | J52: =H52/B52-1 -> 0.6 | K52: =E52/B52-1 -> 0.012
A53: Ionograma | B53: 458.95 | D53: 3.5 | E53: =D53*$M$43 -> 1771 | F53: 3500 | H53: =F53*$M$44 -> 2800 | I53: =H53-E53 -> 1029 | J53: =H53/B53-1 -> 5.1008824 | K53: =E53/B53-1 -> 2.8588081
A54: Uremia | B54: 1000 | D54: 1.5 | E54: =D54*$M$43 -> 759 | F54: 1500 | H54: =F54*$M$44 -> 1200 | I54: =H54-E54 -> 441 | J54: =H54/B54-1 -> 0.2 | K54: =E54/B54-1 -> -0.241
A55: Zinc | B55: 4338.93 | C55: =(D55/$C$64)*$B$64 -> 1257.764 | D55: 15 | E55: =D55*$M$43 -> 7590 | F55: 15000 | H55: =F55*$M$44 -> 12000 | I55: =H55-E55+C55 -> 5667.764 | J55: =H55/B55-1 -> 1.7656588 | K55: =E55/B55-1 -> 0.7492792
A56: Colesterol LDL | B56: 1000 | D56: 4.5 | E56: =D56*$M$43 -> 2277 | F56: 4500 | H56: =F56*$M$44 -> 3600 | I56: =H56-E56 -> 1323 | J56: =H56/B56-1 -> 2.6 | K56: =E56/B56-1 -> 1.277
A57: Colesterol HDL | B57: 1000 | D57: 3 | E57: =D57*$M$43 -> 1518 | F57: 3000 | H57: =F57*$M$44 -> 2400 | I57: =H57-E57 -> 882 | J57: =H57/B57-1 -> 1.4 | K57: =E57/B57-1 -> 0.518
A58: Vitamina D | B58: 4290.72 | D58: 37 | E58: =D58*$M$43 -> 18722 | F58: 37000 | H58: =F58*$M$44 -> 29600 | I58: =H58-E58 -> 10878 | J58: =H58/B58-1 -> 5.8986091 | K58: =E58/B58-1 -> 3.3633703
A59: Selenio | B59: 7985.54 | C59: =(D59/$C$64)*$B$64 -> 1677.0186 | D59: 20 | E59: =D59*$M$43 -> 10120 | F59: 20000 | H59: =F59*$M$44 -> 16000 | I59: =H59-E59+C59 -> 7557.0186 | J59: =H59/B59-1 -> 1.0036215 | K59: =E59/B59-1 -> 0.26729063
A60: Vitamina B1 | B60: 6095 | C60: =(D60/$C$64)*$B$64 -> 2515.528 | D60: 30 | E60: =D60*$M$43 -> 15180 | F60: 30000 | H60: =F60*$M$44 -> 24000 | I60: =H60-E60+C60 -> 11335.528 | J60: =H60/B60-1 -> 2.9376538 | K60: =E60/B60-1 -> 1.490566
A61: Vitamina B6 | B61: 6095 | C61: =(D61/$C$64)*$B$64 -> 3102.4845 | D61: 37 | E61: =D61*$M$43 -> 18722 | F61: 37000 | H61: =F61*$M$44 -> 29600 | I61: =H61-E61+C61 -> 13980.484 | J61: =H61/B61-1 -> 3.8564397 | K61: =E61/B61-1 -> 2.0716981
A62: Vitamina C | B62: 5635 | C62: =(D62/$C$64)*$B$64 -> 2515.528 | D62: 30 | E62: =D62*$M$43 -> 15180 | F62: 30000 | H62: =F62*$M$44 -> 24000 | I62: =H62-E62+C62 -> 11335.528 | J62: =H62/B62-1 -> 3.2590949 | K62: =E62/B62-1 -> 1.6938776
A63: T3 | B63: 428.43 | C63: =(D63/$C$64)*$B$64 -> 754.65839 | D63: 9 | E63: =D63*$M$43 -> 4554 | F63: 9000 | H63: =F63*$M$44 -> 7200 | I63: =H63-E63+C63 -> 3400.6584 | J63: =H63/B63-1 -> 15.805546 | K63: =I63/D63-1 -> 376.85093
B64: 13500 | C64: =D59+D60+D61+D62+D63+D55+D44 -> 161 | I64: =I44+I55+I59+I60+I61+I62+I63 -> 60834
A66: RAHAL MIRTA BEATRIZ | L66: NBU | M66: 642
A67: Inmunocomplejos circulantes (CIC) | B67: =19657.61 -> 19657.61 | C67: 6750 | D67: 30 | E67: =D67*M43 -> 15180 | F67: 30000 | H67: =B67*1.15 -> 22606.251 | I67: =H67-E67+C67 -> 14176.252 | J67: =H67/B67-1 -> 0.15 | K67: =E67/B67-1 -> -0.22777998 | L67: Descuento | M67: 0.8
L68: Descuento | M68: 0.9
A70: GIGENA LUCIO | B70: Costo | C70: 6750 | D70: UB | E70: Pami | F70: COBICO | H70: Importe | I70: Facturado
A71: Helicobacter Pylori, aire espirado | B71: 13650 | D71: 47 | E71: =D71*M66 -> 30174 | F71: 73000 | H71: 65000 | I71: =H71-E71 -> 34826 | J71: =H71/B71-1 -> 3.7619048 | K71: =E71/B71-1 -> 1.2105495 | L71: Descuento | M71: 0.8
A73: MARIN ISABEL DEL VALLE | B73: Costo | D73: UB | E73: Pami | F73: COBICO | H73: Importe | I73: Facturado
A75: Elastasa pancreatica | B75: =30094.53 -> 30094.53 | C75: 13500 | D75: 96 | E75: =D75*M73 -> 0 | F75: 120000 | H75: =F75*M75 -> 0 | I75: =H75-E75+C75 -> 13500
A77: PAEZ, NORBERTO | B77: NO APLICA | D77: UB | E77: Pami | F77: COBICO | H77: Importe | I77: Facturado | L77: NBU | M77: 642
A78: Fibrinogeno | B78: 524.25 | D78: 4 | E78: =D78*$M$77 -> 2568 | F78: 12000 | H78: =F78*$M$78 -> 9180 | J78: =E78/SUM(B78:C78)-1 -> 3.8984263 | M78: 0.765
A79: Antitrombina III funcional | B79: 5997 | C79: =(D79/$C$89)*$B$89 -> 748.33703 | D79: 25 | E79: =D79*$M$77 -> 16050 | F79: 25000 | H79: =F79*$M$78 -> 19125 | I79: =H79-E79+C79 -> 3823.337 | J79: =E79/SUM(B79:C79)-1 -> 1.3794215
A80: Beta 2 Glicoproteina IgG | B80: 7380 | C80: =(D80/$C$89)*$B$89 -> 898.00443 | D80: 30 | E80: =D80*$M$77 -> 19260 | F80: 30000 | H80: =F80*$M$78 -> 22950 | I80: =H80-E80+C80 -> 4588.0044 | J80: =E80/SUM(B80:C80)-1 -> 1.3266477
A81: Beta 2 Glicoproteina IgA | B81: 7380 | C81: =(D81/$C$89)*$B$89 -> 898.00443 | D81: 30 | E81: =D81*$M$77 -> 19260 | F81: 30000 | H81: =F81*$M$78 -> 22950 | I81: =H81-E81+C81 -> 4588.0044 | J81: =E81/SUM(B81:C81)-1 -> 1.3266477
A82: Cardiolipinas IgG | B82: 3875.5 | C82: =(D82/$C$89)*$B$89 -> 538.80266 | D82: 18 | E82: =D82*$M$77 -> 11556 | F82: 18000 | H82: =F82*$M$78 -> 13770 | I82: =H82-E82+C82 -> 2752.8027 | J82: =E82/SUM(B82:C82)-1 -> 1.617854
A83: Cardiolipinas IgM | B83: 3875.5 | C83: =(D83/$C$89)*$B$89 -> 538.80266 | D83: 18 | E83: =D83*$M$77 -> 11556 | F83: 18000 | H83: =F83*$M$78 -> 13770 | I83: =H83-E83+C83 -> 2752.8027 | J83: =E83/SUM(B83:C83)-1 -> 1.617854
A84: Factor V | B84: 19720 | C84: =(D84/$C$89)*$B$89 -> 2843.6807 | D84: 95 | E84: =D84*$M$77 -> 60990 | F84: 95000 | H84: =F84*$M$78 -> 72675 | I84: =H84-E84+C84 -> 14528.681 | J84: =E84/SUM(B84:C84)-1 -> 1.7030164
A85: Homocisteina | B85: 3403.5 | C85: =(D85/$C$89)*$B$89 -> 898.00443 | D85: 30 | E85: =D85*$M$77 -> 19260 | F85: 30000 | H85: =F85*$M$78 -> 22950 | I85: =H85-E85+C85 -> 4588.0044 | J85: =E85/SUM(B85:C85)-1 -> 3.4775032
A86: Proteina C funcional | B86: 10717.2 | C86: =(D86/$C$89)*$B$89 -> 1347.0067 | D86: 45 | E86: =D86*$M$77 -> 28890 | F86: 45000 | H86: =F86*$M$78 -> 34425 | I86: =H86-E86+C86 -> 6882.0067 | J86: =E86/SUM(B86:C86)-1 -> 1.3946871
A87: Proteina S funcional | B87: 11680.61 | C87: =(D87/$C$89)*$B$89 -> 2544.3459 | D87: 85 | E87: =D87*M77 -> 54570 | F87: 85000 | H87: =F87*$M$78 -> 65025 | I87: =H87-E87+C87 -> 12999.346 | J87: =E87/SUM(B87:C87)-1 -> 2.8362158
A88: Protrombina 20.210 | B88: 19719.15 | C88: =(D88/$C$89)*$B$89 -> 2245.0111 | D88: 75 | E88: =D88*$M$77 -> 48150 | F88: 75000 | H88: =F88*$M$78 -> 57375 | I88: =H88-E88+C88 -> 11470.011 | J88: =E88/SUM(B88:C88)-1 -> 1.1922076
B89: 13500 | C89: =D79+D80+D81+D82+D83+D84+D85+D86+D87+D88 -> 451 | I89: =SUM(I78:I88) -> 68973
A90: ALEGRE ANA MARIA | B90: Costo | D90: UB | E90: Pami | F90: COBICO | H90: Importe | I90: Facturado | J90: OCTUBRE | L90: NBU | M90: 355
A91: C1 inhibidor Q | B91: 5473.3 | C91: =6500/2 -> 3250 | D91: 30 | E91: =D91*M90 -> 10650 | F91: 30000 | H91: =F91*0.7 -> 21000 | I91: =H91-E91 -> 10350
A92: C3 | B92: 818.73 | C92: =C91/2 -> 1625 | D92: 5 | E92: =D92*M90 -> 1775 | F92: 5000
A93: C4 | B93: 818.73 | C93: 1625 | D93: 5 | E93: =D93*M90 -> 1775 | F93: 5000
A96: ZOGBE ANTONIO JESÚS | B96: Costo | D96: UB | E96: Pami | F96: COBICO | H96: Importe | I96: Facturado | J96: OCTUBRE | L96: NBU | M96: 355
A97: Calcemia total | D97: 1.5 | E97: =D97*$M$96 -> 532.5 | F97: 1500 | H97: =F97*$M$97 -> 1200 | I97: =H97-E97+C97 -> 667.5 | M97: 0.8
A98: Colesterol total | D98: 1.5 | E98: =D98*$M$96 -> 532.5 | F98: 1500 | H98: =F98*$M$97 -> 1200 | I98: =H98-E98+C98 -> 667.5
A99: Creatinina en sangre | D99: 3 | E99: =D99*$M$96 -> 1065 | F99: 3000 | H99: =F99*$M$97 -> 2400 | I99: =H99-E99+C99 -> 1335
A100: Glucemia | D100: 1.5 | E100: =D100*$M$96 -> 532.5 | F100: 1500 | H100: =F100*$M$97 -> 1200 | I100: =H100-E100+C100 -> 667.5
A101: Hemograma | D101: 5 | E101: =D101*$M$96 -> 1775 | F101: 5000 | H101: =F101*$M$97 -> 4000 | I101: =H101-E101+C101 -> 2225
A102: Orina completa | D102: 5 | E102: =D102*$M$96 -> 1775 | F102: 5000 | H102: =F102*$M$97 -> 4000 | I102: =H102-E102+C102 -> 2225
A103: Trigliceridos | D103: 2.5 | E103: =D103*$M$96 -> 887.5 | F103: 2500 | H103: =F103*$M$97 -> 2000 | I103: =H103-E103+C103 -> 1112.5
A104: Uremia | D104: 1.5 | E104: =D104*$M$96 -> 532.5 | F104: 1500 | H104: =F104*$M$97 -> 1200 | I104: =H104-E104+C104 -> 667.5
A105: Antigeno prostatico especifico total | B105: 1021.23 | D105: 18 | E105: =D105*$M$96 -> 6390 | F105: 18000 | H105: =F105*$M$97 -> 14400 | I105: =H105-E105+C105 -> 8010
A106: Colesterol LDL | D106: 4.5 | E106: =D106*$M$96 -> 1597.5 | F106: 4500 | H106: =F106*$M$97 -> 3600 | I106: =H106-E106+C106 -> 2002.5
A107: Catecolaminas | B107: 11151.38 | C107: =D107/$D$113*$C$113 -> 3375 | D107: 25 | E107: =D107*$M$96 -> 8875 | F107: 25000 | H107: =F107*$M$97 -> 20000 | I107: =H107-E107+C107 -> 14500
A108: Cortisol plasmatico | B108: 802.89 | D108: 12 | E108: =D108*$M$96 -> 4260 | F108: 12000 | H108: =F108*$M$97 -> 9600 | I108: =H108-E108+C108 -> 5340
A109: Cortisol libre urinario | B109: 1182.59 | D109: 10 | E109: =D109*$M$96 -> 3550 | F109: 10000 | H109: =F109*$M$97 -> 8000 | I109: =H109-E109+C109 -> 4450
A110: Normetanefrina urinaria | B110: 18900.48 | C110: =D110/$D$113*$C$113 -> 3375 | D110: 25 | E110: =D110*$M$96 -> 8875 | F110: 25000 | H110: =F110*$M$97 -> 20000 | I110: =H110-E110+C110 -> 14500
A111: Hormona adrenocorticotrofa | B111: 1134.29 | D111: 12 | E111: =D111*$M$96 -> 4260 | F111: 12000 | H111: =F111*$M$97 -> 9600 | I111: =H111-E111+C111 -> 5340
A112: Ionograma plasmatico | D112: 3.5 | E112: =D112*$M$96 -> 1242.5 | F112: 3500 | H112: =F112*$M$97 -> 2800 | I112: =H112-E112+C112 -> 1557.5
C113: 6750 | D113: =D110+D107 -> 50 | I113: =I107+I110 -> 29000
A115: GIGENA, LUCIO | B115: Costo | C115: 6750 | D115: UB | E115: Pami | F115: COBICO | H115: Importe | I115: Facturado | J115: OCTUBRE
A116: Helicobacter Pylori, aire espirado | B116: 13650 | D116: 47 | E116: =D116*M116 -> 30174 | F116: 73000 | H116: 67500 | I116: =H116-E116 -> 37326 | J116: =H116/B116-1 -> 3.9450549 | K116: =E116/B116-1 -> 1.2105495 | L116: NBU | M116: 642
...

Sheet Delgado
A1: Maria Andrea Delgado | H1: 0.3 | I1: 0.3
H2: 0.3 | I2: 0.3
A3: Valores actualizados al mes de ABRIL2026 | F3: 0.01 | H3: 0.25 | I3: 0.2
A4: Prestaciones | B4: Derivación | C4: Derivante | D4: Envío | E4: Viaticos | F4: Costo Interno | G4: COBICO | H4: Importe | I4: Importe | J4: Valor Anterior
A5: ESTUDIO MICROBIOMA INTESTINAL | B5: 297460 | C5: CIBIC | D5: 20000 | E5: 0 | F5: =B5*$F$3 -> 2974.6 | H5: =+SUM(B5:F5)*(1+$H$2) -> 416564.98 | I5: =H5 -> 416564.98 | J5: 397850.57 | K5: =H5/J5-1 -> 0.047038791
A6: DAO | B6: 204016.32 | C6: MANLAB | D6: 20000 | E6: 0 | F6: =B6*$F$3 -> 2040.1632 | H6: =+SUM(B6:F6)*(1+$H$2) -> 293873.43 | I6: =+SUM(C6:G6)*(1+$H$2) -> 28652.212 | J6: 385965.52 | K6: =H6/J6-1 -> -0.23860186
A7: POLIMORFIMOS DE DAO | B7: 299909 | C7: CIBIC | D7: 20000 | E7: 0 | F7: =B7*$F$3 -> 2999.09 | H7: =+SUM(B7:F7)*(1+$H$2) -> 419780.52 | I7: =+SUM(C7:G7)*(1+$H$2) -> 29898.817 | J7: 404491.3 | K7: =H7/J7-1 -> 0.03779863
A8: ALFA 1 ANTITRIPSINA (Mat Fecal) | B8: 7197.36 | C8: GORNITZ | D8: 2500 | E8: 0 | F8: =B8*$F$3 -> 71.9736 | H8: =H9 -> 23625 | I8: =I9 -> 44349.704 | J8: 17142.85 | K8: =H8/J8-1 -> 0.37812557 | L8: 12508.41
A9: ALFA 1 ANTITRIPSINA CLEARENCE | B9: 11515.69 | C9: GORNITZ | D9: 2500 | E9: 0 | F9: =B9*$F$3 -> 115.1569 | G9: 31500 | H9: =G9*(1-$H$3) -> 23625 | I9: =+SUM(C9:G9)*(1+$H$2) -> 44349.704 | J9: 17142.85 | K9: =H9/J9-1 -> 0.37812557
A10: ALFA 1 ANTITRIPSINA EN SUERO | B10: 2554.03 | C10: MANLAB | D10: 2500 | E10: 0 | F10: =B10*$F$3 -> 25.5403 | G10: 15750 | H10: =+H9 -> 23625 | I10: =+I9 -> 44349.704 | J10: 17142.85 | K10: =H10/J10-1 -> 0.37812557
A11: CALPROTECTINA CUANTITATIVA | B11: 32697.94 | C11: MANLAB | D11: 20000 | E11: 0 | F11: =B11*$F$3 -> 326.9794 | G11: 157500 | H11: =G11*(1-$H$1) -> 110250 | I11: =H11*(1-$H$1) -> 77175 | J11: 70981.48 | K11: =H11/J11-1 -> 0.55322205
A12: CREATININA EN ORINA | B12: 0 | D12: 0 | E12: 0 | F12: 4215 | G12: 4725 | H12: =G12*(1-$H$1) -> 3307.5 | I12: =H12*(1-$H$1) -> 2315.25 | J12: 2960 | K12: =H12/J12-1 -> 0.11739865
A13: ELASTASA EN MATERIA FECAL | B13: 85049 | C13: CIBIC | D13: 0 | E13: 0 | F13: =B13*$F$3 -> 850.49 | G13: 189000 | H13: =G13*(1-$H$1) -> 132300 | I13: =H13*(1-$H$1) -> 92610 | J13: 115600.58 | K13: =H13/J13-1 -> 0.14445793 | L13: 115600.58
A14: EXAMEN FUNCIONAL MAT. FECAL (FIS-QUIM) | B14: 0 | D14: 0 | F14: 42150 | G14: 47250 | H14: =G14*(1-$H$1) -> 33075 | I14: =H14*(1-$H$1) -> 23152.5 | J14: 24500 | K14: =H14/J14-1 -> 0.35 | L14: 24500
A15: IGA (MAT. FECAL) | B15: 8000 | D15: 0 | E15: 0 | F15: =B15*$F$3 -> 80 | H15: =+SUM(B15:F15)*(1+$H$2) -> 10504 | I15: =+SUM(C15:G15)*(1+$H$2) -> 104 | J15: 10465 | K15: =H15/J15-1 -> 0.0037267081 | L15: 10465
A16: GRASA CUANTITATIVA MAT. FECAL VAN DE KAMER | B16: 0 | D16: 0 | E16: 0 | F16: 17500 | G16: 23625 | H16: =G16*(1-$H$1) -> 16537.5 | I16: =H16*(1-$H$1) -> 11576.25 | J16: 12250 | K16: =H16/J16-1 -> 0.35
A17: PARASITOLOGICO SERIADO (MAT. FECAL) | B17: 0 | D17: 0 | E17: 0 | F17: 5000 | G17: 6300 | H17: =G17*(1-$H$3) -> 4725 | I17: =H17*(1-$H$1) -> 3307.5 | J17: 3500 | K17: =H17/J17-1 -> 0.35
A18: SANGRE OCULTA INMUNOLOGICO (SIN DIETA) | B18: 0 | D18: 0 | E18: 0 | F18: 9600 | G18: 12600 | H18: =G18*(1-$H$3) -> 9450 | I18: =H18*(1-$H$3) -> 7087.5 | J18: 8550 | K18: =H18/J18-1 -> 0.10526316
A19: SANGRE OCULTA (CON DIETA) | B19: 0 | D19: 0 | E19: 0 | F19: 9600 | G19: 12600 | H19: =G19*(1-$H$3) -> 9450 | I19: =H19*(1-$H$3) -> 7087.5 | J19: 8550 | K19: =H19/J19-1 -> 0.10526316 | L19: 8550
A20: ESCOBILLADO ANAL | D20: 0 | E20: 0 | F20: 4000 | G20: 4725 | H20: =G20*(1-$H$3) -> 3543.75 | I20: =H20*(1-$H$3) -> 2657.8125 | J20: 3200 | K20: =H20/J20-1 -> 0.10742188
A21: MICOLOGICO | B21: 3939.4 | C21: BIOCON | D21: 2500 | F21: =B21*$F$3 -> 39.394 | G21: 22050 | H21: =G21*(1-$H$3) -> 16537.5 | I21: =H21*(1-$H$1) -> 11576.25 | J21: 8433.73 | K21: =H21/J21-1 -> 0.96087615 | L21: 8653.72
A22: ESTEATOCRITO CADA MUESTRA | B22: 0 | D22: 0 | E22: 0 | F22: 10025 | G22: 14175 | H22: =G22*(1-$H$3) -> 10631.25 | I22: =H22*(1-$H$1) -> 7441.875 | J22: 8020 | K22: =H22/J22-1 -> 0.32559227
A23: COPROCULTIVO | B23: 4175.22 | C23: BIOCON | D23: 2250 | F23: =B23*$F$3 -> 41.7522 | G23: 15750 | H23: =G23*(1-$H$3) -> 11812.5 | I23: =H23*(1-$H$1) -> 8268.75 | J23: 8180.16 | K23: =H23/J23-1 -> 0.44404266
A24: AG HELICOBACTER PYLORI | B24: 12151.15 | C24: GORNITZ | D24: 0 | E24: 1000 | F24: =B24*$F$3 -> 121.5115 | G24: 44100 | H24: =G24*(1-$H$3) -> 33075 | I24: =H24*(1-$H$1) -> 23152.5 | J24: 15357.57 | K24: =H24/J24-1 -> 1.153661 | L24: $16375,12
A25: MTHFR | B25: 28890.64 | C25: MANLAB | D25: 20000 | E25: 1200 | F25: =B25*$F$3 -> 288.9064 | G25: 118125 | H25: =G25*(1-$H$3) -> 88593.75 | I25: =H25*(1-$H$1) -> 62015.625 | J25: 61834.67 | K25: =H25/J25-1 -> 0.43275205 | L25: 64590.02
A26: TEST AIRE ESP . LACTOSA | E26: 0 | F26: 82000 | H26: =F26 -> 82000 | I26: =G26 | J26: FALSE | K26: =H26/J26-1 -> #DIV/0!
A27: TEST AIRE ESP. FRUCTUOSA | E27: 0 | F27: 82000 | H27: =F27 -> 82000 | I27: =G27 | J27: FALSE | K27: =H27/J27-1 -> #DIV/0!
A28: TEST AIRE ESP. SIBO | E28: 0 | F28: 86000 | H28: =F28 -> 86000 | I28: =G28 | J28: FALSE | K28: =H28/J28-1 -> #DIV/0!
A29: TEST AIRE ESP. H PYLORI | E29: 0 | F29: 135000 | H29: =F29 -> 135000 | I29: =G29 | J29: FALSE | K29: =H29/J29-1 -> #DIV/0!
A30: TEST DE INTOLERANCIA ALIMENTARIA 105 ALIMENTOS | E30: 0 | F30: 130000 | G30: 135000 | H30: =F30 -> 130000 | I30: =G30 -> 135000 | J30: FALSE | K30: =H30/J30-1 -> #DIV/0!
A31: TEST DE INTOLERANCIA ALIMENTARIA 63 ALIMENTOS | E31: 0 | F31: 85000 | G31: 92000 | H31: =F31 -> 85000 | I31: =G31 -> 92000 | J31: FALSE | K31: =H31/J31-1 -> #DIV/0!
A32: ALEX 2 | B32: 607684 | C32: CIBIC | D32: 20000 | E32: 0 | F32: =B32*$F$3 -> 6076.84 | H32: =+SUM(B32:F32)*(1+$H$2) -> 823889.09 | I32: =+SUM(C32:G32)*(1+$H$2) -> 33899.892
A33: CLOSTRIDIUM | B33: 16996.78 | C33: MANLAB | E33: 0 | F33: =B33*$F$3 -> 169.9678 | G33: 157500 | H33: =G33*(1-$H$1) -> 110250 | I33: =H33*(1-$H$1) -> 77175

Sheet Dra. Selva 
A1: Dra. Selva | G1: 0.6
G2: 0.35
A3: Valores actualizados al mes de ABRIL2026 | E3: 0.05 | G3: 0.12
A4: Prestaciones | B4: Derivación | C4: Derivante | D4: Envío | E4: Costo Interno | F4: COBICO | G4: Importe
A5: ESTUDIO MICROBIOMA INTESTINAL | B5: 297460 | C5: CIBIC | D5: 20000 | E5: =B5*$E$3 -> 14873 | G5: =+SUM(B5:E5)*(1+$G$2) -> 448649.55
A6: DAO | B6: 204016.32 | C6: MANLAB | D6: 20000 | E6: =B6*$E$3 -> 10200.816 | G6: =+SUM(B6:E6)*(1+$G$2) -> 316193.13
A7: ALFA 1 ANTITRIPSINA (Mat Fecal) | B7: 7197.36 | C7: GORNITZ | D7: 2500 | E7: =B7*$E$3 -> 359.868 | G7: =G8 -> 27720
A8: ALFA 1 ANTITRIPSINA CLEARENCE | B8: 11515.69 | C8: GORNITZ | D8: 2500 | E8: =B8*$E$3 -> 575.7845 | F8: 31500 | G8: =F8*(1-$G$3) -> 27720
A9: ALFA 1 ANTITRIPSINA EN SUERO | B9: 2554.03 | C9: MANLAB | D9: 2500 | E9: =B9*$E$3 -> 127.7015 | F9: 15750 | G9: =+G8 -> 27720
A10: CALPROTECTINA CUANTITATIVA | B10: 32697.94 | C10: MANLAB | D10: 20000 | E10: =B10*$E$3 -> 1634.897 | F10: 157500 | G10: =F10*(1-$G$3) -> 138600
A11: ELASTASA EN MATERIA FECAL | B11: 85049 | C11: CIBIC | D11: 0 | E11: =B11*$E$3 -> 4252.45 | F11: 189000 | G11: =F11*(1-$G$3) -> 166320
A12: ZONULINA | B12: 134400 | C12: IACA | D12: 20000 | E12: =B12*0.12 -> 16128 | G12: =SUM(B12:E12)*(1+G1) -> 272844.8
A13: PANEL DE PERMEABILIDAD INTESTINAL(Zonulina-Elastasa-Calprotectina-Alfa 1 Antitripsina) | B13: =SUM(B12) -> 134400 | D13: 20000 | E13: =SUM(E12) -> 16128 | G13: =SUM(G9:G12)*(1-G3) -> 532826.62
A14: AG HELICOBACTER PYLORI | B14: 12151.15 | C14: GORNITZ | D14: 0 | E14: =B14*$E$3 -> 607.5575 | F14: 44100 | G14: =F14*(1-$G$3) -> 38808
A15: TEST AIRE ESP . LACTOSA | E15: 84000 | G15: =E15 -> 84000
A16: TEST AIRE ESP. FRUCTUOSA | E16: 84000 | G16: =E16 -> 84000
A17: TEST AIRE ESP. SIBO | E17: 88000 | G17: =E17 -> 88000
A18: TEST AIRE ESP. H PYLORI | E18: 140000 | G18: =E18 -> 140000
A19: TEST DE INTOLERANCIA ALIMENTARIA 105 ALIMENTOS | E19: 135000 | G19: =E19 -> 135000
A20: TEST DE INTOLERANCIA ALIMENTARIA 63 ALIMENTOS | E20: 92000 | G20: =E20 -> 92000
A21: ALEX 2 | B21: 607684 | C21: CIBIC | D21: 20000 | E21: =B21*$E$3 -> 30384.2 | G21: =+SUM(B21:E21)*(1+$G$2) -> 888392.07
A22: HLA DQ2/DQ8 | B22: 85124 | D22: 20000 | E22: =B22*$E$3 -> 4256.2 | F22: 252000 | G22: =F22*(1-$G$3) -> 221760

Sheet Convenios Particulares
A1: Laboratorio JUJUY
C2: 0.79
A3: Valores Abril 26 - Mayo 26 | C3: 0.8
A4: Prestaciones | B4: Costo Interno | C4: Costo hasta el 31/05/26 | D4: Tiempo de demora estimado | E4: Tipo de Muestra
A5: TEST DE INTOLERANCIA ALIMENTARIA 105 ALIMENTOS | B5: 135000 | C5: =MROUND(B5*$C$2,500) -> 106500 | D5: 72hs recibida la muestra | E5: Sangre entera con citrato de sodio(2,5ml)
A6: TEST DE INTOLERANCIA ALIMENTARIA 63 ALIMENTOS | B6: 92000 | C6: =MROUND(B6*$C$2,500) -> 72500 | D6: 72hs recibida la muestra | E6: Sangre entera con citrato de sodio(2,5ml)
A7: =Cotizador!A8 -> DAO | B7: =Cotizador!H8 -> 316192.68 | C7: =B7*0.92 -> 290897.27 | D7: 72hs recibida la muestra | E7: Sangre entera con citrato de sodio(2,5ml)
A9: NOTA: Costo de envío a cargo del Laboratorio.
A13: Laboratorio Castillo-Chidiak
A15: Valores actualizados al mes de DICIEMBRE 2025
A16: Prestaciones | B16: Costo Interno | C16: Costo | D16: Tiempo de demora estimado | E16: Tipo de Muestra
A17: TEST AIRE ESP . LACTOSA | B17: 80000 | C17: 79000 | D17: 24 horas | E17: Se extrae la muestra en el laboratorio
A18: TEST AIRE ESP. FRUCTUOSA | B18: 80000 | C18: 79000 | D18: 24 horas | E18: Se extrae la muestra en el laboratorio
A19: TEST AIRE ESP. SIBO | B19: 85000 | C19: 84000 | D19: 24 horas | E19: Se extrae la muestra en el laboratorio
A20: TEST AIRE ESP. H PYLORI | B20: 128000 | C20: 128000 | D20: 20 días hábiles | E20: Se extrae la muestra en el laboratorio
A21: TEST DE INTOLERANCIA ALIMENTARIA 105 ALIMENTOS | B21: 128000 | C21: 128000 | D21: 72hs | E21: Sangre entera con citrato de sodio(5ml)
A22: TEST DE INTOLERANCIA ALIMENTARIA 63 ALIMENTOS | B22: 85000 | C22: 85000 | D22: 72hs | E22: Sangre entera con citrato de sodio(5ml)
A24: NOTA: Estos valores se facturan una vez realizado el test. Condición de pago contado (transferencia)
A27: OSPECOR
A29: Valores actualizados al mes de Septiembre 2025
A30: Prestaciones | B30: Costo | C30: Costo | D30: Tiempo de demora estimado | E30: Tipo de Muestra
A31: TEST AIRE ESP . LACTOSA | B31: =B17 -> 80000 | C31: =B31 -> 80000 | D31: 24 horas | E31: Se extrae la muestra en el laboratorio
A32: TEST AIRE ESP. FRUCTUOSA | B32: =B31 -> 80000 | C32: =B32 -> 80000 | D32: 24 horas | E32: Se extrae la muestra en el laboratorio
A33: TEST AIRE ESP. SIBO | B33: =B19 -> 85000 | C33: =B33 -> 85000 | D33: 24 horas | E33: Se extrae la muestra en el laboratorio
A34: TEST AIRE ESP. H PYLORI | B34: =B20 -> 128000 | C34: =B34 -> 128000 | D34: 20 días hábiles | E34: Se extrae la muestra en el laboratorio
A36: NOTA: Estos valores se facturan una vez realizado el test. Condición de pago contado (transferencia)

Sheet Lab Clinico Noelia Dutto
A1: Lab Clínico Noelia Dutto | B1: 0.3
A2: Valores actualizados al mes de Agosto 2025 | B2: 0.3
A4: Prestaciones | B4: Importe | C4: ACTUALIZADO
A5: ESTUDIO MICROBIOMA INTESTINAL | B5: =VLOOKUP(A5,Delgado!A:H,7,0) | C5: FALSE
A6: DAO | B6: =VLOOKUP(A6,Delgado!A:H,7,0) | C6: FALSE
A7: POLIMORFIMOS DE DAO | B7: =VLOOKUP(A7,Delgado!A:H,7,0) | C7: FALSE
A8: ALFA 1 ANTITRIPSINA (Mat Fecal) | B8: =VLOOKUP(A8,Delgado!A:H,7,0) | C8: FALSE
A9: ALFA 1 ANTITRIPSINA CLEARENCE | B9: =VLOOKUP(A9,Delgado!A:H,7,0) -> 31500 | C9: FALSE
A10: ALFA 1 ANTITRIPSINA EN SUERO | B10: =VLOOKUP(A10,Delgado!A:H,7,0) -> 15750 | C10: FALSE
A11: CALPROTECTINA CUANTITATIVA | B11: =VLOOKUP(A11,Delgado!A:H,7,0) -> 157500 | C11: FALSE
A12: ELASTASA EN MATERIA FECAL | B12: =VLOOKUP(A12,Delgado!A:H,7,0) -> 189000 | C12: FALSE
A13: EXAMEN FUNCIONAL MAT. FECAL (FIS-QUIM) | B13: =VLOOKUP(A13,Delgado!A:H,7,0) -> 47250 | C13: FALSE
A14: IGA (MAT. FECAL) | B14: =VLOOKUP(A14,Delgado!A:H,7,0) | C14: FALSE
A15: GRASA CUANTITATIVA MAT. FECAL VAN DE KAMER | B15: =VLOOKUP(A15,Delgado!A:H,7,0) -> 23625 | C15: FALSE
A16: TEST DE INTOLERANCIA ALIMENTARIA 105 ALIMENTOS | B16: =125000*0.8 -> 100000 | C16: FALSE
A17: TEST DE INTOLERANCIA ALIMENTARIA 63 ALIMENTOS | B17: =82500*0.8 -> 66000 | C17: FALSE

Sheet Panel BioM. Int.Panel 
A1: Panel Biomarcador Institucional
H2: 0.6
E3: 0.12 | I3: 0.25 | J3: 0.25
A4: Prestaciones | B4: Derivación | C4: DERIVACION | D4: Envío | E4: Costo Interno | F4: Costo Total | G4: COBICO | H4: PARTICULAR | I4: O.SOCIAL MINIMO | J4: DERIVACION | K4: Margen
A5: ELASTASA | B5: 85049 | C5: CIBIC | D5: 0 | E5: =B5*$E$3 -> 10205.88 | F5: =SUM(B5:E5) -> 95254.88 | G5: 168600 | H5: =G5*0.9 -> 151740 | I5: =H5*0.8 -> 121392 | J5: =I5 -> 121392 | K5: =I5-F5 -> 26137.12
A6: ALFA 1 ANTITRIPSINA | B6: 7197.36 | C6: GORNITZ | D6: 0 | E6: =B6*$E$3 -> 863.6832 | F6: =SUM(B6:E6) -> 8061.0432 | H6: 22000 | I6: =H6*0.8 -> 17600 | J6: =I6 -> 17600 | K6: =I6-F6 -> 9538.9568
A7: CALPROTECTINA | B7: 32697.94 | C7: MANLAB | D7: 0 | E7: =B7*$E$3 -> 3923.7528 | F7: =SUM(B7:E7) -> 36621.693 | G7: 140500 | H7: =G7*0.9 -> 126450 | I7: =H7*0.8 -> 101160 | J7: =H7*0.8 -> 101160 | K7: =I7-F7 -> 64538.307
A8: ZONULINA | B8: 134400 | C8: IACA | D8: 20000 | E8: =B8*$E$3 -> 16128 | F8: =SUM(B8:E8) -> 170528 | H8: =F8*(1+$H$2) -> 272844.8 | I8: =H8*0.8 -> 218275.84 | J8: =I8 -> 218275.84 | K8: =I8-F8 -> 47747.84
A10: PANEL COMPLETO | B10: =SUM(B5:B8) -> 259344.3 | D10: =SUM(D5:D8) -> 20000 | E10: =SUM(E5:E8) -> 31121.316 | F10: =SUM(F5:F8) -> 310465.62 | H10: =SUM(H5:H8)*(1-$H$11) -> 515731.32 | I10: =SUM(I5:I8)*(1-$I$11) -> 435506.45 | J10: =SUM(J5:J8)*(1-$I$11) -> 435506.45 | K10: =I10-F10 -> 125040.83
H11: 0.1 | I11: 0.05

Sheet O. SOCIALES 
A1: ABRIL
A2: OBRA SOCIAL | B2: ANALISIS | C2: COSTO DERIVACION | D2: LUGAR DE DERIVACION | E2: COBICO | F2: NBU | G2: COBERTURA OBRA SOCIAL
A3: SWISS | B3: Calprotectina | C3: 32697.94 | D3: MANLAB | E3: 140500 | F3: 100 | G3: 41537.49 | H3: =G3-C3 -> 8839.55
B4: Elastasa | C4: 85049 | D4: CIBIC | E4: 168600 | F4: 120 | G4: 53330.41 | H4: =G4-B4 -> #VALUE!
B5: HLA DQ2-DQ8 | C5: 85124 | D5: CIBIC | E5: 224800 | F5: 160 | G5: 47097.23 | H5: No sabemos si incluye a los dos o solo uno
A6: GALENO | B6: Calprotectina | C6: 32697.94 | D6: MANLAB | E6: 140500 | F6: 100 | G6: 68053.21
B7: Elastasa | C7: 85049 | D7: CIBIC | E7: 168600 | F7: 120 | G7: 111408.3
B8: HLA DQ2-DQ8 | C8: 85124 | D8: CIBIC | E8: 224800 | F8: 160 | G8: 111408.3
A9: MEDIFE | B9: Calprotectina | C9: 32697.94 | D9: MANLAB | E9: 140500 | F9: 100
B10: Elastasa | C10: 85049 | D10: CIBIC | E10: 168600 | F10: 120
B11: HLA DQ2-DQ8 | C11: 85124 | D11: CIBIC | E11: 224800 | F11: 160
